Workbook

Sheet classified
A1: StudyInstanceUID | B1: Report | C1: ACL | D1: MCL | E1: Medial Meniscus | F1: Lateral Meniscus | G1: Medial OA | H1: Lateral OA | I1: PF OA | J1: Effusion | K1: Synovitis | L1: Baker's | M1: Contusion | N1: Fracture | O1: Language
A2: 1.2.826.0.1.3680043.8.498.10004873229099053869093324292195817260 | B2: Técnica: RMN de la rodilla. Resultados: Rotura de menisco interno. Signo de necrosis avascular subcondral en el cóndilo femoral medial. Artrosis femorotibial medial. Derrame. . Impresión: Rotura de menisco interno. Signo de necrosis avascular subcondral en el cóndilo femoral medial. Artrosis femorotibial medial. Derrame. | C2: 0 | D2: 0 | E2: 0 | F2: 0 | G2: 0 | H2: 0 | I2: 0 | J2: 1 | K2: 0 | L2: 0 | M2: 0 | N2: 0 | O2: Spanish
A3: 1.2.826.0.1.3680043.8.498.10004945927472656027199792075652399585 | B3: [DATE]: * MR Knie Rechts 15ch AA Klinische Inlichtingen: [DATE]. Diagnostische vraagstellling: Meniscusscheur/mediaal? Scanprotocol (DRB) : sag intermediair gewogen seq zonder en met fs, ax/ cor pd gewogen seq fs, cor T1 gewogen seq Bevindingen: | C3: 0 | D3: 0 | E3: 0 | F3: 0 | G3: 0 | H3: 0 | I3: 0 | J3: 0 | K3: 0 | L3: 0 | M3: 0 | N3: 0 | O3: Dutch
A4: 1.2.826.0.1.3680043.8.498.10009278692606631573540062909909132231 | B4: Hallazgos: No hay alteraciones en significativas de la médula ósea. Ligamentos cruzados y colaterales dentro de límites normales. Aumento de señal del cuerno posterior del menisco medial que no impresiona contactar con la superficie articular, sin caracteres propios de rotura. Menisco lateral de morfología y señal conservada, sin signos de rotura. Úlceras condrales de espesor parcial con fenómenos condrales reparativos de la región central de la zona de carga del cóndilo femoral medial. El resto de los cartílagos femorotibiales y de la tróclea femoral sin alteraciones. Úlceras condrales espesor parcial de la rótula de distribución difusa. No hay evidente derrame articular ni quistes poplíteos. Engrosamiento y aumento de señal del tercio proximal del tendón rotuliano y de la inserción distal del tendón cuadricipital con cambios entesopáticos. Tendones de la pata de ganso, bíceps femoral y banda iliotibial dentro de límites normales. Edema las partes blandas entre la banda iliotibial y el cóndilo femoral lateral sugiriendo fenómenos de fricción. Impresión: Condropatía con lesiones grado 2 y 3 asociado a fenómenos condrales reparativos de la región central de la zona de carga del cóndilo femoral medial. Condropatía lesiones grado 2 de la rótula. Tendinosis rotuliana proximal y cuadricipital distal con cambios entesopáticos. Fenómenos de fricción de la banda iliotibial, correlacionar con clínica | C4: 0 | D4: 0 | E4: 0 | F4: 0 | G4: 0 | H4: 0 | I4: 0 | J4: 0 | K4: 0 | L4: 0 | M4: 0 | N4: 0 | O4: Spanish
A5: 1.2.826.0.1.3680043.8.498.10009639203170750274174707434356622764 | B5: In the medial compartment, the meniscus is not torn and there is no focal chondrosis or chondral injury. The lateral compartment, there is suspicious incomplete discoid lateral meniscus without tear. There is no focal chondrosis or chondral injury. The patellofemoral joint, the patellar and trochlear cartilage appears congruent without chondral lesion. The medial patellofemoral ligament is intact. In the intercondylar notch, the anterior and posterior cruciate ligaments are intact. There is no tibial translation. The medial collateral ligament complexes are intact. The posteromedial oblique ligament is intact. The lateral collateral ligament complexes are intact. The popliteofibular ligament is intact. The meniscopopliteal fascicles are intact. The extensor mechanism is normal. No knee effusion is present. The surrounding musculature is normal. There is no fracture or bone contusion. Suspicious incomplete discoid lateral meniscus without tear. Intact cartilage and ligaments of left knee. | C5: 0 | D5: 0 | E5: 0 | F5: 1 | G5: 0 | H5: 0 | I5: 0 | J5: 0 | K5: 0 | L5: 0 | M5: 0 | N5: 0 | O5: English
A6: 1.2.826.0.1.3680043.8.498.10013663742400736029415768216599146542 | B6: CONSTATATIONS : Fractures : Aucune. Alignement articulaire : Normal. Changements dégénératifs : Chondropatie rétropatellaire modérée à sévère avec fissuration profonde impliquant les facettes médiale et latérale, au niveau de la facette médiale et œdème osseux réactionnel [grade 4]. Chondropatie légère des surfaces portantes des compartiments médial et latéral sans fissuration profonde. Signal de la moelle osseuse : Par ailleurs normal. Ligament croisé antérieur : Normal. Ligament croisé postérieur : Normal. Ligament collatéral médial : Léger épaississement proximal compatible avec une ancienne entorse de bas grade. Complexe du ligament collatéral latéral : normal. Ménisque médial : Légers changements dégénératifs dégénérés sans signe de signe. Ménisque latéral : Normal. Tendons extenseurs : Normal. Rétinacula patellaire : Normal. Pes anserinus : Normal. Coin postéro-latéral et postérieur : Normal. Épanchement articulaire : Pas de liquide significatif. Kyste de Baker : Aucun. Autres trouvailles significatives : Aucune. CONCLUSION : Chondropatie rétropatellaire modérée à sévère. Entorse ancienne de bas grade du ligament collatéral médial. Pas de déchirure méniscale. | C6: 0 | D6: 1 | E6: 0 | F6: 0 | G6: 0 | H6: 0 | I6: 0 | J6: 1 | K6: 0 | L6: 0 | M6: 0 | N6: 1 | O6: French
A7: 1.2.826.0.1.3680043.8.498.10018552945042470316597008531304016339 | B7: Antecedentes Clínicos: Condromalacia rotuliana. Hallazgos: No hay alteraciones difusas de señal de la médula ósea. Ligamentos cruzados y colaterales de grosor y señal normales. Menisco medial de morfología normal, con discreto edema de la unión meniscocapsular, inespecífico. Menisco lateral de morfología y señal normal, sin signos de rotura. Cartílago de compartimentos femorotibiales y patelofemoral de grosor y señal normal. No hay derrame articular. No hay quistes poplíteos. Leve aumento de señal de fibras proximales del tendón patelar. Tendones del cuádriceps, poplíteo, semimembranoso, bíceps femoral, banda iliotibial y tendones de la pata de ganso de grosor y señal normales. Edema del cojinete graso suprapatelar retrocuadricipital. Discreto edema del tejido adiposo entre los tendones del sartorio, grácil y el cóndilo femoral medial. También hay discreto edema del tejido adiposo entre el cóndilo femoral lateral y la banda iliotibial. Grupos musculares de trofismo y señal conservados. Impresión: Edema del cojinete graso suprapatelar retrocuadricipital, hallazgo inespecífico, podría representar fenómenos de mal alineamiento patelar. Leve tendinosis patelar proximal. Signos que sugieren fenómenos de fricción posteromedial y de la banda iliotibial, correlacionar con clínica | C7: 0 | D7: 0 | E7: 0 | F7: 0 | G7: 0 | H7: 0 | I7: 0 | J7: 0 | K7: 0 | L7: 0 | M7: 0 | N7: 0 | O7: Spanish
A8: 1.2.826.0.1.3680043.8.498.10018749256316287542884435387067561101 | B8: MRI of left knee with -Locator, SG PD FatSat, SG T2W FS, SG T1W, CO T2W FS, AX T2W FS Findings: > The contour of anterior cruciate ligament is in a straight line but increase signal intensity inside, likely due to sprain > One cystic lesion posterior to ACL, maybe due to ganglion cyst > The contour of posterior cruciate ligaments appearing within normal limit > No definite tear of medial or lateral meniscus in this study > Normal appearance of medial and lateral collateral ligaments > No significant bone marrow edema or active cortical destruction in distal femur, proximal tibia and fibula in this study. > Minimal joint effusion Impression: 1. ACL sprain 2. Suspect ACL ganglion cyst Suggest correlation with clinical manifestation. | C8: 1 | D8: 0 | E8: 0 | F8: 0 | G8: 0 | H8: 0 | I8: 0 | J8: 1 | K8: 0 | L8: 0 | M8: 0 | N8: 0 | O8: English
A9: 1.2.826.0.1.3680043.8.498.10021179701366615563817491713738306606 | B9: МР находка: МР данни за ставен излив. Костите, формиращи дясната коляно са със непроменена структура. Малък костномозъчен едем локализиран в медиалния кондил на тибията. Артикулиращият хрущял на фемура и тибията е изтънен от медиалната страна на ставата. Няма МР данни за руптура на предната кръстна връзка. Нормално представена задна кръстна връзка. Изобразява се увреда в задния рог на медиалния менискус – 2b степен. Нормално представен латерален менискус. Колатерални лигаменти със запазена цялост. Патела, хрущял на пателата, ретинакулуми – б.о. Заключение: МР данни за парциална увреда на задния рог на медиалния менискус – степен 2b. Остеоартритни промени, по-изразени от медиалната страна на колянната става. Бекерова киста. Малък ставен излив. | C9: 0 | D9: 0 | E9: 0 | F9: 0 | G9: 0 | H9: 0 | I9: 0 | J9: 0 | K9: 0 | L9: 0 | M9: 0 | N9: 0 | O9: Cyrillic (Bulgarian/Russian/etc.)
A10: 1.2.826.0.1.3680043.8.498.10021288557171866794624317186288618513 | B10: SOL DİZ MRG. Tetkik protokolü: Çok düzlemli, çok sekanslı. Bulgular: Lateral menisküs ve medial menisküs normaldir. Ön çapraz bağ ve arka çapraz bağ, lateral ve medial kollateral ligaman normaldir.Distal kuadriseps ve patellar tendonlar normaldir. Patella normal yerleşimlidir. Retinaküler devamsızlık yoktur.Diz ekleminde minimal mayii artışı görüldü.Diz eklemini oluşturan kemik yapıların sinyal intensiteleri doğaldır.Sonuç: Diz ekleminde minimal mayii artışı dışından normal sınırlarda bulgular. | C10: 0 | D10: 0 | E10: 0 | F10: 0 | G10: 0 | H10: 0 | I10: 0 | J10: 0 | K10: 0 | L10: 0 | M10: 0 | N10: 0 | O10: Turkish
A11: 1.2.826.0.1.3680043.8.498.10025765742726180988537955593315007559 | B11: MRI of left Knee with -Locator, SG PD FatSat, SG T1W, SG T2W FS, CO T2W FS, AX T2W FS > Fracture of posterior tibial intercondylar eminence with avulsion fracture of PCL. Bone marrow edema in proximal tibia. > The contour of PCL is not all in a straight line and increase signal intensity inside, in favor of partial tear. > The contour of ACL appears to be within normal, no abnormal signal intensity is noted. > Linear signal intensity in posterior horn of medial meniscus and anterior horn of lateral meniscus with extending into the surface, R/O tear. > Both medial & lateral collateral ligaments appear to be within normal. > Joint effusion and suprapatellar bursitis with suprapatellar and medial plicae; hypertrophy of the synovium, indicative of synovitis. Deep infrapatellar bursitis. > Joint effusion and suprapatellar bursitis with suprapatellar and medial plicae; hypertrophy of the synovium with some fatty frondlike excrescences ectending from the synovial surface over lateral suprapatellar region, in favor of synovitis and R/O lipoma arborescens (diffuse synovial lipoma) > Bone marrow edema over mdeial aspect of medial femoral condyle. > Subcutaneous and muscle edema over left knee > Wearing of articular cartilage and spur formation with subchondral edema Impression: 1. Posterior tibial intercondylar eminence fracture with avulsion fracture of PCL and partial tear of PCL. 2. Bone contusion in medial femoral condyle and tibial plateau. 3. Osteoarthritis of left knee. 4. Degeneration of medial and lateral meniscus and R/O tear of anterior horn of lateral meniscus and posterior horn of medial meniscus. 5. Synovitis of left knee with suprapatellar and deep infrapatellar bursitis; R/O lipoma arborescens over lateral aspect of left knee. 6. Subcutaneous and muscle edema over left knee. Suggest correlation with clinical manifestation | C11: 1 | D11: 0 | E11: 1 | F11: 1 | G11: 1 | H11: 0 | I11: 0 | J11: 1 | K11: 1 | L11: 0 | M11: 1 | N11: 1 | O11: English
A12: 1.2.826.0.1.3680043.8.498.10026410865298348818136520318965356394 | B12: Findings: There is a mild knee effusion. There is degenerate tearing of the posterior body and horn of the medial meniscus. Moderate - severe thinning of the medial compartment articular cartilage is noted with mild underlying bony change. Normal lateral meniscus. The lateral compartment articular cartilage is preserved. Normal ACL, PCL, MCL and LCL. Normal extensor mechanism. Moderate thinning of the patellar articular cartilage is noted with minor underlying bony change. Normal trochlear articular cartilage. Conclusion: Medial compartment degeneration with degenerate tearing of the medial meniscus. Grade 2 patellar chondromalacia noted. | C12: 0 | D12: 0 | E12: 1 | F12: 0 | G12: 1 | H12: 0 | I12: 1 | J12: 1 | K12: 0 | L12: 0 | M12: 0 | N12: 0 | O12: English
A13: 1.2.826.0.1.3680043.8.498.10029168398037940681915299760479434938 | B13: Antecedentes Clínicos: Síndrome meniscal rodilla derecha. Hallazgos: No hay alteraciones de señal significativas de la médula ósea. Ligamentos cruzados y colaterales sin alteraciones. Discreto edema de la grasa entre los ligamentos cruzados, en especial rodeando LCP, inespecífica. Meniscos impresionan de morfología y señal conservada, sin criterios de una rotura categórica. Condropatía superficial de platillo tibial lateral. El resto de los cartílagos femorotibiales y de la tróclea femoral sin alteraciones. Úlceras condrales espesor parcial del vértice y faceta medial de la rótula. No hay derrame articular ni quistes poplíteos. Discreto edema las partes blandas entre la banda iliotibial y el cóndilo femoral lateral. No hay alteraciones de señal de la grasa de Hoffa. Impresión: Condropatía superficial de platillo tibial lateral. Condropatía lesiones grado 1 y 2 de la rótula. Probables fenómenos de fricción de la banda iliotibial. Discreto edema de la grasa entre los ligamentos cruzados, en especial rodeando LCP, inespecífico | C13: 0 | D13: 0 | E13: 0 | F13: 0 | G13: 0 | H13: 0 | I13: 0 | J13: 0 | K13: 0 | L13: 0 | M13: 0 | N13: 0 | O13: Spanish
... A4408: 1.2.826.0.1.3680043.8.498.99957611207313098696146908027229590966 | B4408: Técnica: RMN de la rodilla. Resultados: Rotura de fibras del tendón rotuliano. Impresión: Rotura de fibras del tendón rotuliano. | C4408: 0 | D4408: 0 | E4408: 0 | F4408: 0 | G4408: 0 | H4408: 0 | I4408: 0 | J4408: 0 | K4408: 0 | L4408: 0 | M4408: 0 | N4408: 0 | O4408: Spanish

Sheet classified (2)
A1: StudyInstanceUID | B1: Report | C1: ACL | D1: MCL | E1: Medial Meniscus | F1: Lateral Meniscus | G1: Medial OA | H1: Lateral OA | I1: PF OA | J1: Effusion | K1: Synovitis | L1: Baker's | M1: Contusion | N1: Fracture | O1: Language
A2: 1.2.826.0.1.3680043.8.498.10004873229099053869093324292195817260 | B2: Técnica: RMN de la rodilla. Resultados: Rotura de menisco interno. Signo de necrosis avascular subcondral en el cóndilo femoral medial. Artrosis femorotibial medial. Derrame. . Impresión: Rotura de menisco interno. Signo de necrosis avascular subcondral en el cóndilo femoral medial. Artrosis femorotibial medial. Derrame. | C2: 0 | D2: 0 | E2: 0 | F2: 0 | G2: 0 | H2: 0 | I2: 0 | J2: 1 | K2: 0 | L2: 0 | M2: 0 | N2: 0 | O2: Spanish
A3: 1.2.826.0.1.3680043.8.498.10004945927472656027199792075652399585 | B3: [DATE]: * MR Knie Rechts 15ch AA Klinische Inlichtingen: [DATE]. Diagnostische vraagstellling: Meniscusscheur/mediaal? Scanprotocol (DRB) : sag intermediair gewogen seq zonder en met fs, ax/ cor pd gewogen seq fs, cor T1 gewogen seq Bevindingen: | C3: 0 | D3: 0 | E3: 0 | F3: 0 | G3: 0 | H3: 0 | I3: 0 | J3: 0 | K3: 0 | L3: 0 | M3: 0 | N3: 0 | O3: Dutch
A4: 1.2.826.0.1.3680043.8.498.10009278692606631573540062909909132231 | B4: Hallazgos: No hay alteraciones en significativas de la médula ósea. Ligamentos cruzados y colaterales dentro de límites normales. Aumento de señal del cuerno posterior del menisco medial que no impresiona contactar con la superficie articular, sin caracteres propios de rotura. Menisco lateral de morfología y señal conservada, sin signos de rotura. Úlceras condrales de espesor parcial con fenómenos condrales reparativos de la región central de la zona de carga del cóndilo femoral medial. El resto de los cartílagos femorotibiales y de la tróclea femoral sin alteraciones. Úlceras condrales espesor parcial de la rótula de distribución difusa. No hay evidente derrame articular ni quistes poplíteos. Engrosamiento y aumento de señal del tercio proximal del tendón rotuliano y de la inserción distal del tendón cuadricipital con cambios entesopáticos. Tendones de la pata de ganso, bíceps femoral y banda iliotibial dentro de límites normales. Edema las partes blandas entre la banda iliotibial y el cóndilo femoral lateral sugiriendo fenómenos de fricción. Impresión: Condropatía con lesiones grado 2 y 3 asociado a fenómenos condrales reparativos de la región central de la zona de carga del cóndilo femoral medial. Condropatía lesiones grado 2 de la rótula. Tendinosis rotuliana proximal y cuadricipital distal con cambios entesopáticos. Fenómenos de fricción de la banda iliotibial, correlacionar con clínica | C4: 0 | D4: 0 | E4: 0 | F4: 0 | G4: 0 | H4: 0 | I4: 0 | J4: 0 | K4: 0 | L4: 0 | M4: 0 | N4: 0 | O4: Spanish
A5: 1.2.826.0.1.3680043.8.498.10009639203170750274174707434356622764 | B5: In the medial compartment, the meniscus is not torn and there is no focal chondrosis or chondral injury. The lateral compartment, there is suspicious incomplete discoid lateral meniscus without tear. There is no focal chondrosis or chondral injury. The patellofemoral joint, the patellar and trochlear cartilage appears congruent without chondral lesion. The medial patellofemoral ligament is intact. In the intercondylar notch, the anterior and posterior cruciate ligaments are intact. There is no tibial translation. The medial collateral ligament complexes are intact. The posteromedial oblique ligament is intact. The lateral collateral ligament complexes are intact. The popliteofibular ligament is intact. The meniscopopliteal fascicles are intact. The extensor mechanism is normal. No knee effusion is present. The surrounding musculature is normal. There is no fracture or bone contusion. Suspicious incomplete discoid lateral meniscus without tear. Intact cartilage and ligaments of left knee. | C5: 0 | D5: 0 | E5: 0 | F5: 1 | G5: 0 | H5: 0 | I5: 0 | J5: 0 | K5: 0 | L5: 0 | M5: 0 | N5: 0 | O5: English
A6: 1.2.826.0.1.3680043.8.498.10013663742400736029415768216599146542 | B6: CONSTATATIONS : Fractures : Aucune. Alignement articulaire : Normal. Changements dégénératifs : Chondropatie rétropatellaire modérée à sévère avec fissuration profonde impliquant les facettes médiale et latérale, au niveau de la facette médiale et œdème osseux réactionnel [grade 4]. Chondropatie légère des surfaces portantes des compartiments médial et latéral sans fissuration profonde. Signal de la moelle osseuse : Par ailleurs normal. Ligament croisé antérieur : Normal. Ligament croisé postérieur : Normal. Ligament collatéral médial : Léger épaississement proximal compatible avec une ancienne entorse de bas grade. Complexe du ligament collatéral latéral : normal. Ménisque médial : Légers changements dégénératifs dégénérés sans signe de signe. Ménisque latéral : Normal. Tendons extenseurs : Normal. Rétinacula patellaire : Normal. Pes anserinus : Normal. Coin postéro-latéral et postérieur : Normal. Épanchement articulaire : Pas de liquide significatif. Kyste de Baker : Aucun. Autres trouvailles significatives : Aucune. CONCLUSION : Chondropatie rétropatellaire modérée à sévère. Entorse ancienne de bas grade du ligament collatéral médial. Pas de déchirure méniscale. | C6: 0 | D6: 1 | E6: 0 | F6: 0 | G6: 0 | H6: 0 | I6: 0 | J6: 1 | K6: 0 | L6: 0 | M6: 0 | N6: 1 | O6: French
A7: 1.2.826.0.1.3680043.8.498.10018552945042470316597008531304016339 | B7: Antecedentes Clínicos: Condromalacia rotuliana. Hallazgos: No hay alteraciones difusas de señal de la médula ósea. Ligamentos cruzados y colaterales de grosor y señal normales. Menisco medial de morfología normal, con discreto edema de la unión meniscocapsular, inespecífico. Menisco lateral de morfología y señal normal, sin signos de rotura. Cartílago de compartimentos femorotibiales y patelofemoral de grosor y señal normal. No hay derrame articular. No hay quistes poplíteos. Leve aumento de señal de fibras proximales del tendón patelar. Tendones del cuádriceps, poplíteo, semimembranoso, bíceps femoral, banda iliotibial y tendones de la pata de ganso de grosor y señal normales. Edema del cojinete graso suprapatelar retrocuadricipital. Discreto edema del tejido adiposo entre los tendones del sartorio, grácil y el cóndilo femoral medial. También hay discreto edema del tejido adiposo entre el cóndilo femoral lateral y la banda iliotibial. Grupos musculares de trofismo y señal conservados. Impresión: Edema del cojinete graso suprapatelar retrocuadricipital, hallazgo inespecífico, podría representar fenómenos de mal alineamiento patelar. Leve tendinosis patelar proximal. Signos que sugieren fenómenos de fricción posteromedial y de la banda iliotibial, correlacionar con clínica | C7: 0 | D7: 0 | E7: 0 | F7: 0 | G7: 0 | H7: 0 | I7: 0 | J7: 0 | K7: 0 | L7: 0 | M7: 0 | N7: 0 | O7: Spanish
A8: 1.2.826.0.1.3680043.8.498.10018749256316287542884435387067561101 | B8: MRI of left knee with -Locator, SG PD FatSat, SG T2W FS, SG T1W, CO T2W FS, AX T2W FS Findings: > The contour of anterior cruciate ligament is in a straight line but increase signal intensity inside, likely due to sprain > One cystic lesion posterior to ACL, maybe due to ganglion cyst > The contour of posterior cruciate ligaments appearing within normal limit > No definite tear of medial or lateral meniscus in this study > Normal appearance of medial and lateral collateral ligaments > No significant bone marrow edema or active cortical destruction in distal femur, proximal tibia and fibula in this study. > Minimal joint effusion Impression: 1. ACL sprain 2. Suspect ACL ganglion cyst Suggest correlation with clinical manifestation. | C8: 1 | D8: 0 | E8: 0 | F8: 0 | G8: 0 | H8: 0 | I8: 0 | J8: 1 | K8: 0 | L8: 0 | M8: 0 | N8: 0 | O8: English
A9: 1.2.826.0.1.3680043.8.498.10021179701366615563817491713738306606 | B9: МР находка: МР данни за ставен излив. Костите, формиращи дясната коляно са със непроменена структура. Малък костномозъчен едем локализиран в медиалния кондил на тибията. Артикулиращият хрущял на фемура и тибията е изтънен от медиалната страна на ставата. Няма МР данни за руптура на предната кръстна връзка. Нормално представена задна кръстна връзка. Изобразява се увреда в задния рог на медиалния менискус – 2b степен. Нормално представен латерален менискус. Колатерални лигаменти със запазена цялост. Патела, хрущял на пателата, ретинакулуми – б.о. Заключение: МР данни за парциална увреда на задния рог на медиалния менискус – степен 2b. Остеоартритни промени, по-изразени от медиалната страна на колянната става. Бекерова киста. Малък ставен излив. | C9: 0 | D9: 0 | E9: 0 | F9: 0 | G9: 0 | H9: 0 | I9: 0 | J9: 0 | K9: 0 | L9: 0 | M9: 0 | N9: 0 | O9: Cyrillic (Bulgarian/Russian/etc.)
A10: 1.2.826.0.1.3680043.8.498.10021288557171866794624317186288618513 | B10: SOL DİZ MRG. Tetkik protokolü: Çok düzlemli, çok sekanslı. Bulgular: Lateral menisküs ve medial menisküs normaldir. Ön çapraz bağ ve arka çapraz bağ, lateral ve medial kollateral ligaman normaldir.Distal kuadriseps ve patellar tendonlar normaldir. Patella normal yerleşimlidir. Retinaküler devamsızlık yoktur.Diz ekleminde minimal mayii artışı görüldü.Diz eklemini oluşturan kemik yapıların sinyal intensiteleri doğaldır.Sonuç: Diz ekleminde minimal mayii artışı dışından normal sınırlarda bulgular. | C10: 0 | D10: 0 | E10: 0 | F10: 0 | G10: 0 | H10: 0 | I10: 0 | J10: 0 | K10: 0 | L10: 0 | M10: 0 | N10: 0 | O10: Turkish
A11: 1.2.826.0.1.3680043.8.498.10025765742726180988537955593315007559 | B11: MRI of left Knee with -Locator, SG PD FatSat, SG T1W, SG T2W FS, CO T2W FS, AX T2W FS > Fracture of posterior tibial intercondylar eminence with avulsion fracture of PCL. Bone marrow edema in proximal tibia. > The contour of PCL is not all in a straight line and increase signal intensity inside, in favor of partial tear. > The contour of ACL appears to be within normal, no abnormal signal intensity is noted. > Linear signal intensity in posterior horn of medial meniscus and anterior horn of lateral meniscus with extending into the surface, R/O tear. > Both medial & lateral collateral ligaments appear to be within normal. > Joint effusion and suprapatellar bursitis with suprapatellar and medial plicae; hypertrophy of the synovium, indicative of synovitis. Deep infrapatellar bursitis. > Joint effusion and suprapatellar bursitis with suprapatellar and medial plicae; hypertrophy of the synovium with some fatty frondlike excrescences ectending from the synovial surface over lateral suprapatellar region, in favor of synovitis and R/O lipoma arborescens (diffuse synovial lipoma) > Bone marrow edema over mdeial aspect of medial femoral condyle. > Subcutaneous and muscle edema over left knee > Wearing of articular cartilage and spur formation with subchondral edema Impression: 1. Posterior tibial intercondylar eminence fracture with avulsion fracture of PCL and partial tear of PCL. 2. Bone contusion in medial femoral condyle and tibial plateau. 3. Osteoarthritis of left knee. 4. Degeneration of medial and lateral meniscus and R/O tear of anterior horn of lateral meniscus and posterior horn of medial meniscus. 5. Synovitis of left knee with suprapatellar and deep infrapatellar bursitis; R/O lipoma arborescens over lateral aspect of left knee. 6. Subcutaneous and muscle edema over left knee. Suggest correlation with clinical manifestation | C11: 1 | D11: 0 | E11: 1 | F11: 1 | G11: 1 | H11: 0 | I11: 0 | J11: 1 | K11: 1 | L11: 0 | M11: 1 | N11: 1 | O11: English
A12: 1.2.826.0.1.3680043.8.498.10026410865298348818136520318965356394 | B12: Findings: There is a mild knee effusion. There is degenerate tearing of the posterior body and horn of the medial meniscus. Moderate - severe thinning of the medial compartment articular cartilage is noted with mild underlying bony change. Normal lateral meniscus. The lateral compartment articular cartilage is preserved. Normal ACL, PCL, MCL and LCL. Normal extensor mechanism. Moderate thinning of the patellar articular cartilage is noted with minor underlying bony change. Normal trochlear articular cartilage. Conclusion: Medial compartment degeneration with degenerate tearing of the medial meniscus. Grade 2 patellar chondromalacia noted. | C12: 0 | D12: 0 | E12: 1 | F12: 0 | G12: 1 | H12: 0 | I12: 1 | J12: 1 | K12: 0 | L12: 0 | M12: 0 | N12: 0 | O12: English
A13: 1.2.826.0.1.3680043.8.498.10029168398037940681915299760479434938 | B13: Antecedentes Clínicos: Síndrome meniscal rodilla derecha. Hallazgos: No hay alteraciones de señal significativas de la médula ósea. Ligamentos cruzados y colaterales sin alteraciones. Discreto edema de la grasa entre los ligamentos cruzados, en especial rodeando LCP, inespecífica. Meniscos impresionan de morfología y señal conservada, sin criterios de una rotura categórica. Condropatía superficial de platillo tibial lateral. El resto de los cartílagos femorotibiales y de la tróclea femoral sin alteraciones. Úlceras condrales espesor parcial del vértice y faceta medial de la rótula. No hay derrame articular ni quistes poplíteos. Discreto edema las partes blandas entre la banda iliotibial y el cóndilo femoral lateral. No hay alteraciones de señal de la grasa de Hoffa. Impresión: Condropatía superficial de platillo tibial lateral. Condropatía lesiones grado 1 y 2 de la rótula. Probables fenómenos de fricción de la banda iliotibial. Discreto edema de la grasa entre los ligamentos cruzados, en especial rodeando LCP, inespecífico | C13: 0 | D13: 0 | E13: 0 | F13: 0 | G13: 0 | H13: 0 | I13: 0 | J13: 0 | K13: 0 | L13: 0 | M13: 0 | N13: 0 | O13: Spanish
... A4408: 1.2.826.0.1.3680043.8.498.99957611207313098696146908027229590966 | B4408: Técnica: RMN de la rodilla. Resultados: Rotura de fibras del tendón rotuliano. Impresión: Rotura de fibras del tendón rotuliano. | C4408: 0 | D4408: 0 | E4408: 0 | F4408: 0 | G4408: 0 | H4408: 0 | I4408: 0 | J4408: 0 | K4408: 0 | L4408: 0 | M4408: 0 | N4408: 0 | O4408: Spanish

Sheet All Languages Stats
A1: Croatian/Serbian/Bosnian | B1: =COUNTIF('classified (2)'!O411:O4398,A1) -> 370 | D1: 409 | E1: =D1-B1 -> 39 | J1: 4407
A2: Cyrillic (Bulgarian/Russian/etc.) | B2: =COUNTIF('classified (2)'!O412:O4399,A2) -> 194 | D2: 220 | E2: =D2-B2 -> 26
A3: Dutch | B3: =COUNTIF('classified (2)'!O413:O4400,A3) -> 136 | D3: 153 | E3: =D3-B3 -> 17
A4: English | B4: =COUNTIF('classified (2)'!O414:O4401,A4) -> 1545 | D4: 1702 | E4: =D4-B4 -> 157
A5: French | B5: =COUNTIF('classified (2)'!O415:O4402,A5) -> 73 | D5: 81 | E5: =D5-B5 -> 8
A6: German | B6: =COUNTIF('classified (2)'!O416:O4403,A6) -> 229 | D6: 254 | E6: =D6-B6 -> 25
A7: Greek | B7: =COUNTIF('classified (2)'!O417:O4404,A7) -> 298 | D7: 321 | E7: =D7-B7 -> 23
A8: Romanian | B8: =COUNTIF('classified (2)'!O418:O4405,A8) -> 7 | D8: 8 | E8: =D8-B8 -> 1
A9: Spanish | B9: =COUNTIF('classified (2)'!O419:O4406,A9) -> 515 | D9: 573 | E9: =D9-B9 -> 58
A10: Turkish | B10: =COUNTIF('classified (2)'!O420:O4407,A10) -> 497 | D10: 573 | E10: =D10-B10 -> 76
A11: Unknown | B11: =COUNTIF('classified (2)'!O421:O4408,A11) -> 127 | D11: 140 | E11: =D11-B11 -> 13
A12: Total | B12: =SUM(B1:B11) -> 3991 | D12: =SUM(D1:D11) -> 4434 | E12: =D12-B12 -> 443

Sheet Croatian Serbian Bosnian
A1: StudyInstanceUID | B1: ACL | C1: MCL | D1: Medial Meniscus | E1: Lateral Meniscus | F1: Medial OA | G1: Lateral OA | H1: PF OA | I1: Effusion | J1: Synovitis | K1: Baker's | L1: Contusion | M1: Fracture | N1: Language
A2: 1.2.826.0.1.3680043.8.498.10061120822929703004201627784850458401 | B2: 0 | C2: 0 | D2: 1 | E2: 1 | F2: 0 | G2: 0 | H2: 0 | I2: 1 | J2: 0 | K2: 1 | L2: 0 | M2: 0 | N2: Croatian/Serbian/Bosnian
A3: 1.2.826.0.1.3680043.8.498.10088707526476055079083082931629995449 | B3: 0 | C3: 0 | D3: 0 | E3: 0 | F3: 0 | G3: 0 | H3: 0 | I3: 1 | J3: 0 | K3: 0 | L3: 0 | M3: 0 | N3: Croatian/Serbian/Bosnian
A4: 1.2.826.0.1.3680043.8.498.10096216489317602387766193675918767557 | B4: 0 | C4: 1 | D4: 0 | E4: 1 | F4: 0 | G4: 0 | H4: 0 | I4: 1 | J4: 0 | K4: 0 | L4: 0 | M4: 0 | N4: Croatian/Serbian/Bosnian
A5: 1.2.826.0.1.3680043.8.498.10124063607403942330156450768015985834 | B5: 0 | C5: 0 | D5: 0 | E5: 0 | F5: 0 | G5: 0 | H5: 0 | I5: 0 | J5: 0 | K5: 0 | L5: 0 | M5: 0 | N5: Croatian/Serbian/Bosnian
A6: 1.2.826.0.1.3680043.8.498.10128954897472795975323353442305671586 | B6: 0 | C6: 0 | D6: 0 | E6: 0 | F6: 0 | G6: 0 | H6: 0 | I6: 0 | J6: 0 | K6: 0 | L6: 0 | M6: 0 | N6: Croatian/Serbian/Bosnian
A7: 1.2.826.0.1.3680043.8.498.10129462959695121379466274688956171166 | B7: 0 | C7: 0 | D7: 1 | E7: 1 | F7: 0 | G7: 0 | H7: 0 | I7: 1 | J7: 0 | K7: 0 | L7: 0 | M7: 0 | N7: Croatian/Serbian/Bosnian
A8: 1.2.826.0.1.3680043.8.498.10148517526101576084961355066637531019 | B8: 1 | C8: 1 | D8: 1 | E8: 1 | F8: 0 | G8: 0 | H8: 0 | I8: 1 | J8: 0 | K8: 0 | L8: 0 | M8: 0 | N8: Croatian/Serbian/Bosnian
A9: 1.2.826.0.1.3680043.8.498.10218458664774126578027318307405130821 | B9: 0 | C9: 1 | D9: 0 | E9: 1 | F9: 0 | G9: 0 | H9: 0 | I9: 1 | J9: 0 | K9: 0 | L9: 0 | M9: 0 | N9: Croatian/Serbian/Bosnian
A10: 1.2.826.0.1.3680043.8.498.10321556388278642027434955207617064548 | B10: 0 | C10: 0 | D10: 0 | E10: 0 | F10: 0 | G10: 0 | H10: 0 | I10: 0 | J10: 0 | K10: 0 | L10: 0 | M10: 0 | N10: Croatian/Serbian/Bosnian
A11: 1.2.826.0.1.3680043.8.498.10322724865012212544754724404226583315 | B11: 1 | C11: 0 | D11: 1 | E11: 1 | F11: 0 | G11: 0 | H11: 0 | I11: 1 | J11: 0 | K11: 1 | L11: 0 | M11: 0 | N11: Croatian/Serbian/Bosnian
A12: 1.2.826.0.1.3680043.8.498.10352044313309892076985642485759368197 | B12: 0 | C12: 0 | D12: 0 | E12: 1 | F12: 0 | G12: 0 | H12: 0 | I12: 1 | J12: 0 | K12: 0 | L12: 0 | M12: 0 | N12: Croatian/Serbian/Bosnian
A13: 1.2.826.0.1.3680043.8.498.10387227472110643414333498953513810066 | B13: 1 | C13: 0 | D13: 1 | E13: 1 | F13: 0 | G13: 0 | H13: 0 | I13: 1 | J13: 0 | K13: 0 | L13: 0 | M13: 0 | N13: Croatian/Serbian/Bosnian
... A410: 1.2.826.0.1.3680043.8.498.99768154649604643975127490783989114506 | B410: 0 | C410: 0 | D410: 0 | E410: 0 | F410: 0 | G410: 0 | H410: 0 | I410: 1 | J410: 0 | K410: 0 | L410: 0 | M410: 0 | N410: Croatian/Serbian/Bosnian

Sheet Cyrillic Bulgarian Russian etc
A1: StudyInstanceUID | B1: ACL | C1: MCL | D1: Medial Meniscus | E1: Lateral Meniscus | F1: Medial OA | G1: Lateral OA | H1: PF OA | I1: Effusion | J1: Synovitis | K1: Baker's | L1: Contusion | M1: Fracture | N1: Language
A2: 1.2.826.0.1.3680043.8.498.10021179701366615563817491713738306606 | B2: 0 | C2: 0 | D2: 0 | E2: 0 | F2: 0 | G2: 0 | H2: 0 | I2: 0 | J2: 0 | K2: 0 | L2: 0 | M2: 0 | N2: Cyrillic (Bulgarian/Russian/etc.)
A3: 1.2.826.0.1.3680043.8.498.10120841513315425967980213160839994882 | B3: 0 | C3: 0 | D3: 0 | E3: 0 | F3: 0 | G3: 0 | H3: 0 | I3: 0 | J3: 0 | K3: 0 | L3: 0 | M3: 0 | N3: Cyrillic (Bulgarian/Russian/etc.)
A4: 1.2.826.0.1.3680043.8.498.10150914432481980534086434136814789205 | B4: 0 | C4: 0 | D4: 0 | E4: 0 | F4: 0 | G4: 0 | H4: 0 | I4: 0 | J4: 0 | K4: 0 | L4: 0 | M4: 0 | N4: Cyrillic (Bulgarian/Russian/etc.)
A5: 1.2.826.0.1.3680043.8.498.10240237086492917349933491458808329326 | B5: 0 | C5: 0 | D5: 0 | E5: 0 | F5: 0 | G5: 0 | H5: 0 | I5: 0 | J5: 0 | K5: 0 | L5: 0 | M5: 0 | N5: Cyrillic (Bulgarian/Russian/etc.)
A6: 1.2.826.0.1.3680043.8.498.10301089872627496769249366231947887097 | B6: 0 | C6: 0 | D6: 0 | E6: 0 | F6: 0 | G6: 0 | H6: 0 | I6: 0 | J6: 0 | K6: 0 | L6: 0 | M6: 0 | N6: Cyrillic (Bulgarian/Russian/etc.)
A7: 1.2.826.0.1.3680043.8.498.10310831394568337664174691281092566272 | B7: 0 | C7: 0 | D7: 0 | E7: 0 | F7: 0 | G7: 0 | H7: 0 | I7: 0 | J7: 0 | K7: 0 | L7: 0 | M7: 0 | N7: Cyrillic (Bulgarian/Russian/etc.)
A8: 1.2.826.0.1.3680043.8.498.10321702681363532511953946967334431952 | B8: 0 | C8: 0 | D8: 0 | E8: 0 | F8: 0 | G8: 0 | H8: 0 | I8: 0 | J8: 0 | K8: 0 | L8: 0 | M8: 0 | N8: Cyrillic (Bulgarian/Russian/etc.)
A9: 1.2.826.0.1.3680043.8.498.10326352669696598934883805147731461341 | B9: 0 | C9: 0 | D9: 0 | E9: 0 | F9: 0 | G9: 0 | H9: 0 | I9: 0 | J9: 0 | K9: 0 | L9: 0 | M9: 0 | N9: Cyrillic (Bulgarian/Russian/etc.)
A10: 1.2.826.0.1.3680043.8.498.10330805760778577501878048995484987687 | B10: 0 | C10: 0 | D10: 0 | E10: 0 | F10: 0 | G10: 0 | H10: 0 | I10: 0 | J10: 0 | K10: 0 | L10: 0 | M10: 0 | N10: Cyrillic (Bulgarian/Russian/etc.)
A11: 1.2.826.0.1.3680043.8.498.10378535286770237477615181844634903700 | B11: 0 | C11: 0 | D11: 0 | E11: 0 | F11: 0 | G11: 0 | H11: 0 | I11: 0 | J11: 0 | K11: 0 | L11: 0 | M11: 0 | N11: Cyrillic (Bulgarian/Russian/etc.)
A12: 1.2.826.0.1.3680043.8.498.10415616591430643294142401482460086713 | B12: 0 | C12: 0 | D12: 0 | E12: 0 | F12: 0 | G12: 0 | H12: 0 | I12: 0 | J12: 0 | K12: 0 | L12: 0 | M12: 0 | N12: Cyrillic (Bulgarian/Russian/etc.)
A13: 1.2.826.0.1.3680043.8.498.10432568348356281020515782178064869805 | B13: 0 | C13: 0 | D13: 0 | E13: 0 | F13: 0 | G13: 0 | H13: 0 | I13: 0 | J13: 0 | K13: 0 | L13: 0 | M13: 0 | N13: Cyrillic (Bulgarian/Russian/etc.)
... A221: 1.2.826.0.1.3680043.8.498.99813269006669714758887909212386431934 | B221: 0 | C221: 0 | D221: 0 | E221: 0 | F221: 0 | G221: 0 | H221: 0 | I221: 0 | J221: 0 | K221: 0 | L221: 0 | M221: 0 | N221: Cyrillic (Bulgarian/Russian/etc.)

Sheet Dutch
A1: StudyInstanceUID | B1: ACL | C1: MCL | D1: Medial Meniscus | E1: Lateral Meniscus | F1: Medial OA | G1: Lateral OA | H1: PF OA | I1: Effusion | J1: Synovitis | K1: Baker's | L1: Contusion | M1: Fracture | N1: Language
A2: 1.2.826.0.1.3680043.8.498.10004945927472656027199792075652399585 | B2: 0 | C2: 0 | D2: 0 | E2: 0 | F2: 0 | G2: 0 | H2: 0 | I2: 0 | J2: 0 | K2: 0 | L2: 0 | M2: 0 | N2: Dutch
A3: 1.2.826.0.1.3680043.8.498.10182565688010898600749222617373997197 | B3: 0 | C3: 0 | D3: 0 | E3: 0 | F3: 0 | G3: 0 | H3: 0 | I3: 0 | J3: 0 | K3: 0 | L3: 0 | M3: 0 | N3: Dutch
A4: 1.2.826.0.1.3680043.8.498.10201660732108909756259359440298787775 | B4: 0 | C4: 0 | D4: 0 | E4: 0 | F4: 0 | G4: 0 | H4: 0 | I4: 0 | J4: 1 | K4: 0 | L4: 0 | M4: 0 | N4: Dutch
A5: 1.2.826.0.1.3680043.8.498.10287488031206457680758379452936914669 | B5: 0 | C5: 0 | D5: 0 | E5: 0 | F5: 0 | G5: 0 | H5: 0 | I5: 0 | J5: 0 | K5: 0 | L5: 0 | M5: 0 | N5: Dutch
A6: 1.2.826.0.1.3680043.8.498.10374791734880310643587680407133671218 | B6: 0 | C6: 0 | D6: 0 | E6: 0 | F6: 0 | G6: 0 | H6: 0 | I6: 0 | J6: 0 | K6: 0 | L6: 0 | M6: 0 | N6: Dutch
A7: 1.2.826.0.1.3680043.8.498.10603952065748622499432940419853732241 | B7: 0 | C7: 0 | D7: 0 | E7: 0 | F7: 0 | G7: 0 | H7: 0 | I7: 0 | J7: 0 | K7: 0 | L7: 0 | M7: 0 | N7: Dutch
A8: 1.2.826.0.1.3680043.8.498.10652685418462611085839874321267337079 | B8: 0 | C8: 0 | D8: 0 | E8: 0 | F8: 0 | G8: 0 | H8: 0 | I8: 0 | J8: 0 | K8: 0 | L8: 0 | M8: 0 | N8: Dutch
A9: 1.2.826.0.1.3680043.8.498.10674673641872871321890995010616205087 | B9: 0 | C9: 0 | D9: 0 | E9: 0 | F9: 0 | G9: 0 | H9: 0 | I9: 0 | J9: 0 | K9: 0 | L9: 0 | M9: 0 | N9: Dutch
A10: 1.2.826.0.1.3680043.8.498.10751624265599812767108610284996090628 | B10: 1 | C10: 0 | D10: 0 | E10: 0 | F10: 0 | G10: 0 | H10: 0 | I10: 0 | J10: 0 | K10: 0 | L10: 0 | M10: 0 | N10: Dutch
A11: 1.2.826.0.1.3680043.8.498.10818980124981334596808438908811623528 | B11: 0 | C11: 0 | D11: 0 | E11: 0 | F11: 0 | G11: 0 | H11: 0 | I11: 0 | J11: 0 | K11: 0 | L11: 0 | M11: 0 | N11: Dutch
A12: 1.2.826.0.1.3680043.8.498.10842906919708856642000130208791281263 | B12: 0 | C12: 0 | D12: 0 | E12: 0 | F12: 0 | G12: 0 | H12: 0 | I12: 0 | J12: 0 | K12: 0 | L12: 0 | M12: 0 | N12: Dutch
A13: 1.2.826.0.1.3680043.8.498.10876177342063734507664188801203192617 | B13: 0 | C13: 0 | D13: 0 | E13: 0 | F13: 0 | G13: 0 | H13: 0 | I13: 0 | J13: 0 | K13: 0 | L13: 0 | M13: 0 | N13: Dutch
... A154: 1.2.826.0.1.3680043.8.498.99881620336512626242732899010111041290 | B154: 0 | C154: 0 | D154: 0 | E154: 0 | F154: 0 | G154: 0 | H154: 0 | I154: 0 | J154: 0 | K154: 0 | L154: 0 | M154: 0 | N154: Dutch

Sheet English
A1: StudyInstanceUID | B1: ACL | C1: MCL | D1: Medial Meniscus | E1: Lateral Meniscus | F1: Medial OA | G1: Lateral OA | H1: PF OA | I1: Effusion | J1: Synovitis | K1: Baker's | L1: Contusion | M1: Fracture | N1: Language
A2: 1.2.826.0.1.3680043.8.498.10009639203170750274174707434356622764 | B2: 0 | C2: 0 | D2: 0 | E2: 1 | F2: 0 | G2: 0 | H2: 0 | I2: 0 | J2: 0 | K2: 0 | L2: 0 | M2: 0 | N2: English
A3: 1.2.826.0.1.3680043.8.498.10018749256316287542884435387067561101 | B3: 1 | C3: 0 | D3: 0 | E3: 0 | F3: 0 | G3: 0 | H3: 0 | I3: 1 | J3: 0 | K3: 0 | L3: 0 | M3: 0 | N3: English
A4: 1.2.826.0.1.3680043.8.498.10025765742726180988537955593315007559 | B4: 1 | C4: 0 | D4: 1 | E4: 1 | F4: 1 | G4: 0 | H4: 0 | I4: 1 | J4: 1 | K4: 0 | L4: 1 | M4: 1 | N4: English
A5: 1.2.826.0.1.3680043.8.498.10026410865298348818136520318965356394 | B5: 0 | C5: 0 | D5: 1 | E5: 0 | F5: 1 | G5: 0 | H5: 1 | I5: 1 | J5: 0 | K5: 0 | L5: 0 | M5: 0 | N5: English
A6: 1.2.826.0.1.3680043.8.498.10029520033957968044048068502185417806 | B6: 1 | C6: 1 | D6: 1 | E6: 1 | F6: 0 | G6: 1 | H6: 1 | I6: 1 | J6: 1 | K6: 0 | L6: 1 | M6: 0 | N6: English
A7: 1.2.826.0.1.3680043.8.498.10048842414095994814596043262132965018 | B7: 1 | C7: 0 | D7: 0 | E7: 0 | F7: 0 | G7: 0 | H7: 1 | I7: 1 | J7: 0 | K7: 0 | L7: 1 | M7: 1 | N7: English
A8: 1.2.826.0.1.3680043.8.498.10064642360075735959136394136507408269 | B8: 0 | C8: 0 | D8: 0 | E8: 0 | F8: 1 | G8: 0 | H8: 1 | I8: 0 | J8: 0 | K8: 0 | L8: 0 | M8: 0 | N8: English
A9: 1.2.826.0.1.3680043.8.498.10066945398485042741116657288959323922 | B9: 0 | C9: 0 | D9: 1 | E9: 0 | F9: 1 | G9: 0 | H9: 1 | I9: 1 | J9: 0 | K9: 0 | L9: 0 | M9: 0 | N9: English
A10: 1.2.826.0.1.3680043.8.498.10077497528995409346950814927366582736 | B10: 1 | C10: 0 | D10: 1 | E10: 0 | F10: 0 | G10: 0 | H10: 1 | I10: 1 | J10: 0 | K10: 0 | L10: 1 | M10: 1 | N10: English
A11: 1.2.826.0.1.3680043.8.498.10081117556977868957150377234052259018 | B11: 1 | C11: 0 | D11: 1 | E11: 1 | F11: 1 | G11: 1 | H11: 0 | I11: 1 | J11: 0 | K11: 0 | L11: 0 | M11: 0 | N11: English
A12: 1.2.826.0.1.3680043.8.498.10085187975213640798228717119613397941 | B12: 1 | C12: 0 | D12: 1 | E12: 1 | F12: 0 | G12: 0 | H12: 0 | I12: 0 | J12: 0 | K12: 0 | L12: 0 | M12: 0 | N12: English
A13: 1.2.826.0.1.3680043.8.498.10090136633727522725960302994815319097 | B13: 1 | C13: 1 | D13: 1 | E13: 1 | F13: 0 | G13: 0 | H13: 0 | I13: 0 | J13: 0 | K13: 0 | L13: 0 | M13: 0 | N13: English
... A1703: 1.2.826.0.1.3680043.8.498.99939100657291954890286900729983287973 | B1703: 0 | C1703: 0 | D1703: 0 | E1703: 0 | F1703: 0 | G1703: 0 | H1703: 1 | I1703: 1 | J1703: 0 | K1703: 0 | L1703: 0 | M1703: 0 | N1703: English

Sheet French
A1: StudyInstanceUID | B1: ACL | C1: MCL | D1: Medial Meniscus | E1: Lateral Meniscus | F1: Medial OA | G1: Lateral OA | H1: PF OA | I1: Effusion | J1: Synovitis | K1: Baker's | L1: Contusion | M1: Fracture | N1: Language
A2: 1.2.826.0.1.3680043.8.498.10013663742400736029415768216599146542 | B2: 0 | C2: 1 | D2: 0 | E2: 0 | F2: 0 | G2: 0 | H2: 0 | I2: 1 | J2: 0 | K2: 0 | L2: 0 | M2: 1 | N2: French
A3: 1.2.826.0.1.3680043.8.498.10205592316907266136938526795826751183 | B3: 1 | C3: 1 | D3: 0 | E3: 0 | F3: 0 | G3: 0 | H3: 0 | I3: 1 | J3: 0 | K3: 0 | L3: 0 | M3: 1 | N3: French
A4: 1.2.826.0.1.3680043.8.498.10207134048598925821261298801127950516 | B4: 0 | C4: 0 | D4: 0 | E4: 0 | F4: 0 | G4: 0 | H4: 0 | I4: 1 | J4: 0 | K4: 0 | L4: 0 | M4: 0 | N4: French
A5: 1.2.826.0.1.3680043.8.498.10850742579000782417673172155504794301 | B5: 0 | C5: 0 | D5: 0 | E5: 0 | F5: 0 | G5: 0 | H5: 0 | I5: 1 | J5: 0 | K5: 0 | L5: 0 | M5: 0 | N5: French
A6: 1.2.826.0.1.3680043.8.498.10895521387894821238259709507311341758 | B6: 0 | C6: 0 | D6: 0 | E6: 0 | F6: 0 | G6: 0 | H6: 0 | I6: 1 | J6: 0 | K6: 0 | L6: 0 | M6: 0 | N6: French
A7: 1.2.826.0.1.3680043.8.498.10902166579916526176697193295886992412 | B7: 0 | C7: 0 | D7: 0 | E7: 0 | F7: 0 | G7: 0 | H7: 0 | I7: 1 | J7: 0 | K7: 0 | L7: 0 | M7: 1 | N7: French
A8: 1.2.826.0.1.3680043.8.498.10924685588962763768106617368647678902 | B8: 0 | C8: 0 | D8: 0 | E8: 0 | F8: 0 | G8: 0 | H8: 0 | I8: 1 | J8: 0 | K8: 0 | L8: 0 | M8: 1 | N8: French
A9: 1.2.826.0.1.3680043.8.498.11052720536194493057619720620119095739 | B9: 0 | C9: 0 | D9: 0 | E9: 0 | F9: 0 | G9: 0 | H9: 0 | I9: 1 | J9: 0 | K9: 0 | L9: 0 | M9: 0 | N9: French
A10: 1.2.826.0.1.3680043.8.498.11406381777983128446583783158882827226 | B10: 0 | C10: 0 | D10: 0 | E10: 0 | F10: 0 | G10: 0 | H10: 0 | I10: 1 | J10: 0 | K10: 0 | L10: 0 | M10: 0 | N10: French
A11: 1.2.826.0.1.3680043.8.498.11719502398697390809777045891822044637 | B11: 0 | C11: 0 | D11: 0 | E11: 0 | F11: 1 | G11: 1 | H11: 1 | I11: 1 | J11: 0 | K11: 1 | L11: 0 | M11: 1 | N11: French
A12: 1.2.826.0.1.3680043.8.498.11785138333495400389510795613252286069 | B12: 0 | C12: 0 | D12: 0 | E12: 0 | F12: 0 | G12: 0 | H12: 0 | I12: 1 | J12: 1 | K12: 0 | L12: 0 | M12: 0 | N12: French
A13: 1.2.826.0.1.3680043.8.498.11848828525319749834876185415845381479 | B13: 0 | C13: 0 | D13: 0 | E13: 0 | F13: 0 | G13: 0 | H13: 1 | I13: 1 | J13: 0 | K13: 0 | L13: 0 | M13: 0 | N13: French
... A82: 1.2.826.0.1.3680043.8.498.99448612525108835020450967944392129536 | B82: 0 | C82: 0 | D82: 0 | E82: 0 | F82: 0 | G82: 0 | H82: 0 | I82: 1 | J82: 1 | K82: 1 | L82: 0 | M82: 0 | N82: French

Sheet German
A1: StudyInstanceUID | B1: ACL | C1: MCL | D1: Medial Meniscus | E1: Lateral Meniscus | F1: Medial OA | G1: Lateral OA | H1: PF OA | I1: Effusion | J1: Synovitis | K1: Baker's | L1: Contusion | M1: Fracture | N1: Language
A2: 1.2.826.0.1.3680043.8.498.10243300429607935614655219482457289307 | B2: 0 | C2: 0 | D2: 0 | E2: 0 | F2: 0 | G2: 0 | H2: 1 | I2: 0 | J2: 0 | K2: 0 | L2: 0 | M2: 0 | N2: German
A3: 1.2.826.0.1.3680043.8.498.10261794102024899290234062909324134903 | B3: 0 | C3: 0 | D3: 0 | E3: 0 | F3: 0 | G3: 0 | H3: 0 | I3: 0 | J3: 0 | K3: 0 | L3: 0 | M3: 0 | N3: German
A4: 1.2.826.0.1.3680043.8.498.10318366890716843554246682186865048846 | B4: 0 | C4: 0 | D4: 0 | E4: 0 | F4: 0 | G4: 0 | H4: 1 | I4: 1 | J4: 0 | K4: 0 | L4: 0 | M4: 0 | N4: German
A5: 1.2.826.0.1.3680043.8.498.10371162371589200772388569623043753617 | B5: 1 | C5: 0 | D5: 0 | E5: 0 | F5: 1 | G5: 1 | H5: 1 | I5: 1 | J5: 0 | K5: 0 | L5: 0 | M5: 0 | N5: German
A6: 1.2.826.0.1.3680043.8.498.10423586531262405323219596291234698626 | B6: 0 | C6: 0 | D6: 0 | E6: 0 | F6: 0 | G6: 0 | H6: 0 | I6: 1 | J6: 0 | K6: 0 | L6: 0 | M6: 0 | N6: German
A7: 1.2.826.0.1.3680043.8.498.10434135978927658622039675788413759069 | B7: 0 | C7: 1 | D7: 0 | E7: 0 | F7: 0 | G7: 0 | H7: 1 | I7: 0 | J7: 0 | K7: 0 | L7: 1 | M7: 0 | N7: German
A8: 1.2.826.0.1.3680043.8.498.10459044164648238749799867924228983674 | B8: 0 | C8: 0 | D8: 0 | E8: 0 | F8: 0 | G8: 0 | H8: 0 | I8: 1 | J8: 0 | K8: 0 | L8: 0 | M8: 0 | N8: German
A9: 1.2.826.0.1.3680043.8.498.10499265498716562276605625682538326716 | B9: 0 | C9: 0 | D9: 0 | E9: 0 | F9: 0 | G9: 0 | H9: 0 | I9: 1 | J9: 0 | K9: 0 | L9: 0 | M9: 0 | N9: German
A10: 1.2.826.0.1.3680043.8.498.10511712617129216774539441890488742560 | B10: 0 | C10: 0 | D10: 0 | E10: 0 | F10: 0 | G10: 0 | H10: 0 | I10: 0 | J10: 0 | K10: 0 | L10: 0 | M10: 0 | N10: German
A11: 1.2.826.0.1.3680043.8.498.10521372086358356219840179458708706015 | B11: 0 | C11: 0 | D11: 0 | E11: 0 | F11: 0 | G11: 0 | H11: 1 | I11: 0 | J11: 0 | K11: 0 | L11: 0 | M11: 0 | N11: German
A12: 1.2.826.0.1.3680043.8.498.10530226787566708645477257565528473018 | B12: 0 | C12: 0 | D12: 0 | E12: 0 | F12: 0 | G12: 0 | H12: 0 | I12: 0 | J12: 0 | K12: 0 | L12: 0 | M12: 0 | N12: German
A13: 1.2.826.0.1.3680043.8.498.10542526906255526405613760733936070251 | B13: 0 | C13: 0 | D13: 0 | E13: 0 | F13: 0 | G13: 0 | H13: 0 | I13: 0 | J13: 0 | K13: 0 | L13: 0 | M13: 0 | N13: German
... A255: 1.2.826.0.1.3680043.8.498.99864345386635409953374818045984558970 | B255: 0 | C255: 0 | D255: 0 | E255: 0 | F255: 0 | G255: 0 | H255: 1 | I255: 0 | J255: 0 | K255: 0 | L255: 0 | M255: 0 | N255: German

Sheet Greek
A1: StudyInstanceUID | B1: ACL | C1: MCL | D1: Medial Meniscus | E1: Lateral Meniscus | F1: Medial OA | G1: Lateral OA | H1: PF OA | I1: Effusion | J1: Synovitis | K1: Baker's | L1: Contusion | M1: Fracture | N1: Language
A2: 1.2.826.0.1.3680043.8.498.10039686090738454718354181337513293981 | B2: 0 | C2: 0 | D2: 0 | E2: 0 | F2: 0 | G2: 0 | H2: 0 | I2: 0 | J2: 0 | K2: 0 | L2: 0 | M2: 0 | N2: Greek
A3: 1.2.826.0.1.3680043.8.498.10058298717414171145622092128156266866 | B3: 0 | C3: 0 | D3: 0 | E3: 0 | F3: 0 | G3: 0 | H3: 0 | I3: 0 | J3: 0 | K3: 0 | L3: 0 | M3: 0 | N3: Greek
A4: 1.2.826.0.1.3680043.8.498.10077803906105306230229342168184970097 | B4: 0 | C4: 0 | D4: 0 | E4: 0 | F4: 0 | G4: 0 | H4: 0 | I4: 0 | J4: 0 | K4: 0 | L4: 1 | M4: 0 | N4: Greek
A5: 1.2.826.0.1.3680043.8.498.10201197020583611347810070328854760801 | B5: 0 | C5: 0 | D5: 0 | E5: 0 | F5: 0 | G5: 0 | H5: 0 | I5: 0 | J5: 0 | K5: 0 | L5: 1 | M5: 0 | N5: Greek
A6: 1.2.826.0.1.3680043.8.498.10209387047693448282446870911381660585 | B6: 0 | C6: 0 | D6: 0 | E6: 0 | F6: 0 | G6: 0 | H6: 0 | I6: 0 | J6: 0 | K6: 0 | L6: 0 | M6: 0 | N6: Greek
A7: 1.2.826.0.1.3680043.8.498.10240166440044087554182120832488098189 | B7: 0 | C7: 0 | D7: 0 | E7: 0 | F7: 0 | G7: 0 | H7: 0 | I7: 0 | J7: 0 | K7: 0 | L7: 0 | M7: 0 | N7: Greek
A8: 1.2.826.0.1.3680043.8.498.10299396087685174806129850512856451005 | B8: 0 | C8: 0 | D8: 0 | E8: 0 | F8: 0 | G8: 0 | H8: 0 | I8: 0 | J8: 0 | K8: 0 | L8: 0 | M8: 0 | N8: Greek
A9: 1.2.826.0.1.3680043.8.498.10339654093023509742663983374586998753 | B9: 0 | C9: 0 | D9: 0 | E9: 0 | F9: 0 | G9: 0 | H9: 0 | I9: 0 | J9: 0 | K9: 0 | L9: 0 | M9: 0 | N9: Greek
A10: 1.2.826.0.1.3680043.8.498.10524164196949381411165626176732559196 | B10: 0 | C10: 0 | D10: 0 | E10: 0 | F10: 0 | G10: 0 | H10: 0 | I10: 0 | J10: 0 | K10: 0 | L10: 0 | M10: 0 | N10: Greek
A11: 1.2.826.0.1.3680043.8.498.10540980111087702906123811593906850156 | B11: 0 | C11: 0 | D11: 0 | E11: 0 | F11: 0 | G11: 0 | H11: 0 | I11: 0 | J11: 0 | K11: 0 | L11: 0 | M11: 0 | N11: Greek
A12: 1.2.826.0.1.3680043.8.498.10601711635138681269270505152909539290 | B12: 0 | C12: 0 | D12: 0 | E12: 0 | F12: 0 | G12: 0 | H12: 0 | I12: 0 | J12: 0 | K12: 0 | L12: 0 | M12: 0 | N12: Greek
A13: 1.2.826.0.1.3680043.8.498.10626071553432761206594400919097854593 | B13: 0 | C13: 0 | D13: 0 | E13: 0 | F13: 0 | G13: 0 | H13: 0 | I13: 0 | J13: 0 | K13: 0 | L13: 0 | M13: 0 | N13: Greek
... A322: 1.2.826.0.1.3680043.8.498.99303079292320085374389086609761974820 | B322: 0 | C322: 0 | D322: 0 | E322: 0 | F322: 0 | G322: 0 | H322: 0 | I322: 0 | J322: 0 | K322: 0 | L322: 0 | M322: 0 | N322: Greek

Sheet Romanian
A1: StudyInstanceUID | B1: ACL | C1: MCL | D1: Medial Meniscus | E1: Lateral Meniscus | F1: Medial OA | G1: Lateral OA | H1: PF OA | I1: Effusion | J1: Synovitis | K1: Baker's | L1: Contusion | M1: Fracture | N1: Language
A2: 1.2.826.0.1.3680043.8.498.10124701778993602117271554854098856833 | B2: 0 | C2: 0 | D2: 0 | E2: 0 | F2: 0 | G2: 0 | H2: 1 | I2: 1 | J2: 0 | K2: 0 | L2: 0 | M2: 0 | N2: Romanian
A3: 1.2.826.0.1.3680043.8.498.12352132666379687393012255589355771387 | B3: 0 | C3: 0 | D3: 0 | E3: 0 | F3: 0 | G3: 0 | H3: 0 | I3: 0 | J3: 0 | K3: 0 | L3: 1 | M3: 0 | N3: Romanian
A4: 1.2.826.0.1.3680043.8.498.24209643225939781032698894992032106781 | B4: 0 | C4: 0 | D4: 0 | E4: 0 | F4: 1 | G4: 1 | H4: 1 | I4: 0 | J4: 0 | K4: 0 | L4: 0 | M4: 0 | N4: Romanian
A5: 1.2.826.0.1.3680043.8.498.35826402289277331555736683320175912112 | B5: 0 | C5: 0 | D5: 0 | E5: 0 | F5: 0 | G5: 0 | H5: 1 | I5: 0 | J5: 0 | K5: 0 | L5: 1 | M5: 0 | N5: Romanian
A6: 1.2.826.0.1.3680043.8.498.38717329577625255474350472405748992219 | B6: 1 | C6: 1 | D6: 0 | E6: 0 | F6: 0 | G6: 0 | H6: 0 | I6: 0 | J6: 0 | K6: 0 | L6: 0 | M6: 0 | N6: Romanian
A7: 1.2.826.0.1.3680043.8.498.53173579822475854424126184867040523127 | B7: 0 | C7: 0 | D7: 0 | E7: 0 | F7: 0 | G7: 0 | H7: 0 | I7: 0 | J7: 0 | K7: 0 | L7: 0 | M7: 0 | N7: Romanian
A8: 1.2.826.0.1.3680043.8.498.65703265163052901613211590083675186626 | B8: 0 | C8: 0 | D8: 0 | E8: 0 | F8: 1 | G8: 1 | H8: 1 | I8: 1 | J8: 0 | K8: 0 | L8: 0 | M8: 0 | N8: Romanian
A9: 1.2.826.0.1.3680043.8.498.74332475620045145049628676751586693385 | B9: 0 | C9: 1 | D9: 0 | E9: 0 | F9: 0 | G9: 0 | H9: 0 | I9: 1 | J9: 0 | K9: 0 | L9: 0 | M9: 0 | N9: Romanian

Sheet Spanish
A1: StudyInstanceUID | B1: ACL | C1: MCL | D1: Medial Meniscus | E1: Lateral Meniscus | F1: Medial OA | G1: Lateral OA | H1: PF OA | I1: Effusion | J1: Synovitis | K1: Baker's | L1: Contusion | M1: Fracture | N1: Language
A2: 1.2.826.0.1.3680043.8.498.10004873229099053869093324292195817260 | B2: 0 | C2: 0 | D2: 0 | E2: 0 | F2: 0 | G2: 0 | H2: 0 | I2: 1 | J2: 0 | K2: 0 | L2: 0 | M2: 0 | N2: Spanish
A3: 1.2.826.0.1.3680043.8.498.10009278692606631573540062909909132231 | B3: 0 | C3: 0 | D3: 0 | E3: 0 | F3: 0 | G3: 0 | H3: 0 | I3: 0 | J3: 0 | K3: 0 | L3: 0 | M3: 0 | N3: Spanish
A4: 1.2.826.0.1.3680043.8.498.10018552945042470316597008531304016339 | B4: 0 | C4: 0 | D4: 0 | E4: 0 | F4: 0 | G4: 0 | H4: 0 | I4: 0 | J4: 0 | K4: 0 | L4: 0 | M4: 0 | N4: Spanish
A5: 1.2.826.0.1.3680043.8.498.10029168398037940681915299760479434938 | B5: 0 | C5: 0 | D5: 0 | E5: 0 | F5: 0 | G5: 0 | H5: 0 | I5: 0 | J5: 0 | K5: 0 | L5: 0 | M5: 0 | N5: Spanish
A6: 1.2.826.0.1.3680043.8.498.10059200627175320481920009076697103801 | B6: 0 | C6: 0 | D6: 0 | E6: 0 | F6: 0 | G6: 0 | H6: 0 | I6: 0 | J6: 1 | K6: 0 | L6: 0 | M6: 0 | N6: Spanish
A7: 1.2.826.0.1.3680043.8.498.10095687747295410396510538520594649149 | B7: 0 | C7: 0 | D7: 0 | E7: 0 | F7: 0 | G7: 0 | H7: 0 | I7: 1 | J7: 0 | K7: 0 | L7: 0 | M7: 0 | N7: Spanish
A8: 1.2.826.0.1.3680043.8.498.10112440805412493412191181061985753636 | B8: 0 | C8: 0 | D8: 0 | E8: 0 | F8: 0 | G8: 0 | H8: 0 | I8: 0 | J8: 0 | K8: 0 | L8: 0 | M8: 0 | N8: Spanish
A9: 1.2.826.0.1.3680043.8.498.10135587809070718435691939321937314104 | B9: 0 | C9: 0 | D9: 1 | E9: 1 | F9: 0 | G9: 0 | H9: 0 | I9: 1 | J9: 1 | K9: 0 | L9: 0 | M9: 0 | N9: Spanish
A10: 1.2.826.0.1.3680043.8.498.10149967031679082348901055550415519790 | B10: 0 | C10: 0 | D10: 0 | E10: 0 | F10: 0 | G10: 0 | H10: 0 | I10: 0 | J10: 0 | K10: 0 | L10: 0 | M10: 0 | N10: Spanish
A11: 1.2.826.0.1.3680043.8.498.10162168547770229150261479353227398478 | B11: 0 | C11: 0 | D11: 1 | E11: 1 | F11: 0 | G11: 0 | H11: 0 | I11: 0 | J11: 0 | K11: 0 | L11: 0 | M11: 0 | N11: Spanish
A12: 1.2.826.0.1.3680043.8.498.10162720374291180196973998234794414415 | B12: 0 | C12: 0 | D12: 0 | E12: 0 | F12: 0 | G12: 0 | H12: 0 | I12: 0 | J12: 0 | K12: 0 | L12: 0 | M12: 0 | N12: Spanish
A13: 1.2.826.0.1.3680043.8.498.10189392162056736163704940747328177364 | B13: 0 | C13: 0 | D13: 0 | E13: 0 | F13: 0 | G13: 0 | H13: 0 | I13: 1 | J13: 0 | K13: 0 | L13: 0 | M13: 0 | N13: Spanish
... A574: 1.2.826.0.1.3680043.8.498.99957611207313098696146908027229590966 | B574: 0 | C574: 0 | D574: 0 | E574: 0 | F574: 0 | G574: 0 | H574: 0 | I574: 0 | J574: 0 | K574: 0 | L574: 0 | M574: 0 | N574: Spanish

Sheet Turkish
A1: StudyInstanceUID | B1: ACL | C1: MCL | D1: Medial Meniscus | E1: Lateral Meniscus | F1: Medial OA | G1: Lateral OA | H1: PF OA | I1: Effusion | J1: Synovitis | K1: Baker's | L1: Contusion | M1: Fracture | N1: Language
A2: 1.2.826.0.1.3680043.8.498.10021288557171866794624317186288618513 | B2: 0 | C2: 0 | D2: 0 | E2: 0 | F2: 0 | G2: 0 | H2: 0 | I2: 0 | J2: 0 | K2: 0 | L2: 0 | M2: 0 | N2: Turkish
A3: 1.2.826.0.1.3680043.8.498.10088120558600684332737135714636269365 | B3: 0 | C3: 0 | D3: 0 | E3: 0 | F3: 0 | G3: 0 | H3: 0 | I3: 0 | J3: 0 | K3: 0 | L3: 0 | M3: 0 | N3: Turkish
A4: 1.2.826.0.1.3680043.8.498.10096063158753121251217031021181036863 | B4: 0 | C4: 0 | D4: 0 | E4: 0 | F4: 0 | G4: 0 | H4: 0 | I4: 0 | J4: 0 | K4: 0 | L4: 0 | M4: 0 | N4: Turkish
A5: 1.2.826.0.1.3680043.8.498.10096919689272424388113819845481617364 | B5: 0 | C5: 0 | D5: 0 | E5: 0 | F5: 0 | G5: 0 | H5: 0 | I5: 0 | J5: 0 | K5: 0 | L5: 0 | M5: 0 | N5: Turkish
A6: 1.2.826.0.1.3680043.8.498.10121558854084271154265851933273260339 | B6: 0 | C6: 0 | D6: 0 | E6: 0 | F6: 0 | G6: 0 | H6: 0 | I6: 0 | J6: 0 | K6: 0 | L6: 0 | M6: 0 | N6: Turkish
A7: 1.2.826.0.1.3680043.8.498.10123751739767586025744123799948754343 | B7: 0 | C7: 0 | D7: 0 | E7: 0 | F7: 0 | G7: 0 | H7: 0 | I7: 0 | J7: 0 | K7: 0 | L7: 0 | M7: 0 | N7: Turkish
A8: 1.2.826.0.1.3680043.8.498.10136486417446492428821313562961937182 | B8: 0 | C8: 1 | D8: 0 | E8: 0 | F8: 0 | G8: 0 | H8: 0 | I8: 0 | J8: 0 | K8: 0 | L8: 0 | M8: 0 | N8: Turkish
A9: 1.2.826.0.1.3680043.8.498.10147180484860577398303524379319212586 | B9: 0 | C9: 1 | D9: 0 | E9: 0 | F9: 0 | G9: 0 | H9: 0 | I9: 0 | J9: 1 | K9: 0 | L9: 0 | M9: 0 | N9: Turkish
A10: 1.2.826.0.1.3680043.8.498.10147717839726734017869499799005084725 | B10: 0 | C10: 0 | D10: 0 | E10: 0 | F10: 0 | G10: 0 | H10: 0 | I10: 0 | J10: 0 | K10: 0 | L10: 0 | M10: 0 | N10: Turkish
A11: 1.2.826.0.1.3680043.8.498.10183939841890895037058579455663880292 | B11: 0 | C11: 0 | D11: 0 | E11: 0 | F11: 0 | G11: 0 | H11: 0 | I11: 0 | J11: 0 | K11: 0 | L11: 0 | M11: 0 | N11: Turkish
A12: 1.2.826.0.1.3680043.8.498.10241639721703882165429374175491428414 | B12: 0 | C12: 0 | D12: 0 | E12: 0 | F12: 0 | G12: 0 | H12: 0 | I12: 0 | J12: 0 | K12: 0 | L12: 0 | M12: 0 | N12: Turkish
A13: 1.2.826.0.1.3680043.8.498.10256441455107860474283716992657597873 | B13: 0 | C13: 1 | D13: 0 | E13: 0 | F13: 0 | G13: 0 | H13: 0 | I13: 0 | J13: 0 | K13: 0 | L13: 0 | M13: 0 | N13: Turkish
... A547: 1.2.826.0.1.3680043.8.498.99926624968240681772735102303531613209 | B547: 0 | C547: 0 | D547: 0 | E547: 0 | F547: 0 | G547: 0 | H547: 0 | I547: 0 | J547: 0 | K547: 0 | L547: 0 | M547: 0 | N547: Turkish

Sheet Unknown
A1: StudyInstanceUID | B1: ACL | C1: MCL | D1: Medial Meniscus | E1: Lateral Meniscus | F1: Medial OA | G1: Lateral OA | H1: PF OA | I1: Effusion | J1: Synovitis | K1: Baker's | L1: Contusion | M1: Fracture | N1: Language
A2: 1.2.826.0.1.3680043.8.498.10087350795575215080051569638065974347 | B2: 0 | C2: 0 | D2: 0 | E2: 0 | F2: 0 | G2: 0 | H2: 0 | I2: 0 | J2: 0 | K2: 0 | L2: 0 | M2: 0 | N2: Unknown
A3: 1.2.826.0.1.3680043.8.498.10133843191898064967257276100779798471 | B3: 0 | C3: 0 | D3: 0 | E3: 0 | F3: 0 | G3: 0 | H3: 0 | I3: 0 | J3: 0 | K3: 0 | L3: 0 | M3: 0 | N3: Unknown
A4: 1.2.826.0.1.3680043.8.498.10199522802568420589167284753473646773 | B4: 0 | C4: 0 | D4: 0 | E4: 0 | F4: 0 | G4: 0 | H4: 0 | I4: 0 | J4: 0 | K4: 0 | L4: 0 | M4: 0 | N4: Unknown
A5: 1.2.826.0.1.3680043.8.498.10211815027850731240126403602239595062 | B5: 0 | C5: 0 | D5: 0 | E5: 0 | F5: 0 | G5: 0 | H5: 0 | I5: 0 | J5: 0 | K5: 0 | L5: 0 | M5: 0 | N5: Unknown
A6: 1.2.826.0.1.3680043.8.498.10299618611626190927173051117228647808 | B6: 0 | C6: 0 | D6: 0 | E6: 0 | F6: 0 | G6: 0 | H6: 0 | I6: 0 | J6: 0 | K6: 0 | L6: 0 | M6: 0 | N6: Unknown
A7: 1.2.826.0.1.3680043.8.498.10349368332722015923160611226877741306 | B7: 0 | C7: 0 | D7: 0 | E7: 0 | F7: 0 | G7: 0 | H7: 0 | I7: 0 | J7: 0 | K7: 0 | L7: 0 | M7: 0 | N7: Unknown
A8: 1.2.826.0.1.3680043.8.498.10351460911387106879135924409514835385 | B8: 0 | C8: 0 | D8: 0 | E8: 0 | F8: 0 | G8: 0 | H8: 0 | I8: 0 | J8: 0 | K8: 0 | L8: 0 | M8: 0 | N8: Unknown
A9: 1.2.826.0.1.3680043.8.498.10540882690103231159064894952851205573 | B9: 0 | C9: 0 | D9: 0 | E9: 0 | F9: 0 | G9: 0 | H9: 0 | I9: 0 | J9: 0 | K9: 0 | L9: 0 | M9: 0 | N9: Unknown
A10: 1.2.826.0.1.3680043.8.498.10593694750925047629619718537436931628 | B10: 0 | C10: 0 | D10: 0 | E10: 0 | F10: 0 | G10: 0 | H10: 0 | I10: 0 | J10: 0 | K10: 0 | L10: 0 | M10: 0 | N10: Unknown
A11: 1.2.826.0.1.3680043.8.498.10848350333764008140459854470293737650 | B11: 0 | C11: 0 | D11: 0 | E11: 0 | F11: 0 | G11: 0 | H11: 0 | I11: 0 | J11: 0 | K11: 0 | L11: 0 | M11: 0 | N11: Unknown
A12: 1.2.826.0.1.3680043.8.498.10994899269366718796438389394954844979 | B12: 0 | C12: 0 | D12: 0 | E12: 0 | F12: 0 | G12: 0 | H12: 0 | I12: 0 | J12: 0 | K12: 0 | L12: 0 | M12: 0 | N12: Unknown
A13: 1.2.826.0.1.3680043.8.498.11148939654362681630811787929668902046 | B13: 0 | C13: 0 | D13: 0 | E13: 0 | F13: 0 | G13: 0 | H13: 0 | I13: 0 | J13: 0 | K13: 0 | L13: 0 | M13: 0 | N13: Unknown
... A141: 1.2.826.0.1.3680043.8.498.99243902497374852166139435719549686908 | B141: 0 | C141: 0 | D141: 0 | E141: 0 | F141: 0 | G141: 0 | H141: 0 | I141: 0 | J141: 0 | K141: 0 | L141: 0 | M141: 0 | N141: Unknown
